sop_voice/__init__.py
sop_voice/filtersets.py
sop_voice/models.py
sop_voice/navigation.py
sop_voice/search.py
sop_voice/urls.py
sop_voice/utils.py
sop_voice/validators.py
sop_voice/api/__init__.py
sop_voice/api/serializers.py
sop_voice/api/urls.py
sop_voice/api/views.py
sop_voice/api/__pycache__/__init__.cpython-310.pyc
sop_voice/api/__pycache__/__init__.cpython-312.pyc
sop_voice/api/__pycache__/serializers.cpython-310.pyc
sop_voice/api/__pycache__/serializers.cpython-312.pyc
sop_voice/api/__pycache__/urls.cpython-310.pyc
sop_voice/api/__pycache__/urls.cpython-312.pyc
sop_voice/api/__pycache__/views.cpython-310.pyc
sop_voice/api/__pycache__/views.cpython-312.pyc
sop_voice/forms/site_voice_info.py
sop_voice/forms/voice_delivery.py
sop_voice/forms/voice_maintainer.py
sop_voice/forms/voice_sda.py
sop_voice/forms/__pycache__/site_voice_info.cpython-310.pyc
sop_voice/forms/__pycache__/site_voice_info.cpython-312.pyc
sop_voice/forms/__pycache__/voice_delivery.cpython-310.pyc
sop_voice/forms/__pycache__/voice_delivery.cpython-312.pyc
sop_voice/forms/__pycache__/voice_maintainer.cpython-310.pyc
sop_voice/forms/__pycache__/voice_maintainer.cpython-312.pyc
sop_voice/forms/__pycache__/voice_sda.cpython-310.pyc
sop_voice/forms/__pycache__/voice_sda.cpython-312.pyc
sop_voice/migrations/0001_initial.py
sop_voice/migrations/0002_voicesda_site_alter_voicesda_delivery_and_more.py
sop_voice/migrations/0003_alter_voicesda_delivery.py
sop_voice/migrations/0004_alter_voicesda_delivery_alter_voicesda_end_and_more.py
sop_voice/migrations/0005_alter_voicesda_end_alter_voicesda_start.py
sop_voice/migrations/0006_alter_voicesda_end_alter_voicesda_start.py
sop_voice/migrations/0007_alter_voicedelivery_dto_alter_voicedelivery_ndi.py
sop_voice/migrations/0008_alter_voicedelivery_channel_count.py
sop_voice/migrations/0009_alter_voicedelivery_channel_count_and_more.py
sop_voice/migrations/0010_alter_voicedelivery_channel_count_and_more.py
sop_voice-1.2.7.dist-info/METADATA
sop_voice-1.2.7.dist-info/WHEEL
sop_voice-1.2.7.dist-info/top_level.txt
sop_voice-1.2.7.dist-info/RECORD
