Metadata-Version: 2.1
Name: sop-voice
Version: 1.2.7
Summary: Manage voice informations of each sites.
Author: Leorevoir
Author-email: leo.quinzler@epitech.eu
Classifier: Framework :: Django
Classifier: Programming Language :: Python :: 3
Requires-Dist: phonenumbers
